eccenca_marketplace_client/__init__.py
eccenca_marketplace_client/exceptions.py
eccenca_marketplace_client/fields.py
eccenca_marketplace_client/image.py
eccenca_marketplace_client/limits.py
eccenca_marketplace_client/models/__init__.py
eccenca_marketplace_client/models/agents.py
eccenca_marketplace_client/models/base.py
eccenca_marketplace_client/models/dependencies.py
eccenca_marketplace_client/models/files.py
eccenca_marketplace_client/models/manifests.py
eccenca_marketplace_client/models/metadata.py
eccenca_marketplace_client/models/responses.py
eccenca_marketplace_client/ontology.py
eccenca_marketplace_client/package_graph.py
eccenca_marketplace_client/package_version.py
eccenca_marketplace_client-0.7.0.dist-info/METADATA
eccenca_marketplace_client-0.7.0.dist-info/WHEEL
eccenca_marketplace_client-0.7.0.dist-info/licenses/LICENSE
eccenca_marketplace_client-0.7.0.dist-info/RECORD
