Metadata-Version: 2.4
Name: eccenca-marketplace-client
Version: 0.7.0
Summary: Models and client for the eccenca Marketplace.
License: Apache-2.0
License-File: LICENSE
Author: eccenca GmbH
Author-email: cmempy-developer@eccenca.com
Requires-Python: >=3.13,<4
Classifier: Development Status :: 4 - Beta
Classifier: License :: OSI Approved :: Apache Software License
Classifier: Programming Language :: Python :: 3
Classifier: Programming Language :: Python :: 3.13
Classifier: Programming Language :: Python :: 3.14
Requires-Dist: license-expression (>=30.4.4,<31.0.0)
Requires-Dist: pydantic-extra-types (>=2.10.4,<3.0.0)
Requires-Dist: pydantic[email] (>=2.12.5,<3.0.0)
Requires-Dist: rdflib (>=7.4.0,<8.0.0)
Requires-Dist: semver (>=3.0.4,<4.0.0)
